<?xml version="1.0" encoding="UTF-8"?>
<MetaDataObject xmlns="http://v8.1c.ru/8.3/MDClasses" xmlns:app="http://v8.1c.ru/8.2/managed-application/core" xmlns:cfg="http://v8.1c.ru/8.1/data/enterprise/current-config" xmlns:cmi="http://v8.1c.ru/8.2/managed-application/cmi" xmlns:ent="http://v8.1c.ru/8.1/data/enterprise" xmlns:lf="http://v8.1c.ru/8.2/managed-application/logform" xmlns:style="http://v8.1c.ru/8.1/data/ui/style" xmlns:sys="http://v8.1c.ru/8.1/data/ui/fonts/system" xmlns:v8="http://v8.1c.ru/8.1/data/core" xmlns:v8ui="http://v8.1c.ru/8.1/data/ui" xmlns:web="http://v8.1c.ru/8.1/data/ui/colors/web" xmlns:win="http://v8.1c.ru/8.1/data/ui/colors/windows" xmlns:xen="http://v8.1c.ru/8.3/xcf/enums" xmlns:xpr="http://v8.1c.ru/8.3/xcf/predef" xmlns:xr="http://v8.1c.ru/8.3/xcf/readable" xmlns:xs="http://www.w3.org/2001/XMLSchema" xmlns:xsi="http://www.w3.org/2001/XMLSchema-instance" version="2.10">
	<Task uuid="812408c2-e1f9-4ffd-817a-afd69d325fea">
		<InternalInfo>
			<xr:GeneratedType name="TaskObject.ЗадачаБилета" category="Object">
				<xr:TypeId>cf25b9d9-38bf-4b74-af9e-1ec233a7d6da</xr:TypeId>
				<xr:ValueId>caec1511-0970-41f5-a059-34242fec5420</xr:ValueId>
			</xr:GeneratedType>
			<xr:GeneratedType name="TaskRef.ЗадачаБилета" category="Ref">
				<xr:TypeId>003e1a93-6c98-4322-aabc-9fa248d7319c</xr:TypeId>
				<xr:ValueId>035f0e48-5264-4354-b4d7-5b1eb586218a</xr:ValueId>
			</xr:GeneratedType>
			<xr:GeneratedType name="TaskSelection.ЗадачаБилета" category="Selection">
				<xr:TypeId>2c741380-bd90-400a-8cd8-a866cc7cde3a</xr:TypeId>
				<xr:ValueId>738ddbde-7bb4-4d81-af69-62784cf9aff2</xr:ValueId>
			</xr:GeneratedType>
			<xr:GeneratedType name="TaskList.ЗадачаБилета" category="List">
				<xr:TypeId>e4f39bea-48ce-4ada-be96-2298a83d90c8</xr:TypeId>
				<xr:ValueId>4e49de6a-35be-45b9-bf20-359ae5072e46</xr:ValueId>
			</xr:GeneratedType>
			<xr:GeneratedType name="TaskManager.ЗадачаБилета" category="Manager">
				<xr:TypeId>87cb6c09-687b-4bad-90bc-dbe2ce34b9f3</xr:TypeId>
				<xr:ValueId>902e1f2e-2779-4f9e-b14c-bbecb7d22fa5</xr:ValueId>
			</xr:GeneratedType>
		</InternalInfo>
		<Properties>
			<Name>ЗадачаБилета</Name>
			<Synonym>
				<v8:item>
					<v8:lang>ru</v8:lang>
					<v8:content>Задача билета</v8:content>
				</v8:item>
			</Synonym>
			<Comment/>
			<UseStandardCommands>true</UseStandardCommands>
			<NumberType>String</NumberType>
			<NumberLength>9</NumberLength>
			<NumberAllowedLength>Variable</NumberAllowedLength>
			<CheckUnique>true</CheckUnique>
			<Autonumbering>true</Autonumbering>
			<TaskNumberAutoPrefix>DontUse</TaskNumberAutoPrefix>
			<DescriptionLength>25</DescriptionLength>
			<Addressing>InformationRegister.РегистрАдресации</Addressing>
			<MainAddressingAttribute>Task.ЗадачаБилета.AddressingAttribute.Исполнитель</MainAddressingAttribute>
			<CurrentPerformer>SessionParameter.ФизЛицо</CurrentPerformer>
			<BasedOn/>
			<Characteristics/>
			<DefaultPresentation>AsDescription</DefaultPresentation>
			<EditType>InDialog</EditType>
			<InputByString>
				<xr:Field>Task.ЗадачаБилета.StandardAttribute.Description</xr:Field>
				<xr:Field>Task.ЗадачаБилета.StandardAttribute.Number</xr:Field>
			</InputByString>
			<SearchStringModeOnInputByString>Begin</SearchStringModeOnInputByString>
			<FullTextSearchOnInputByString>DontUse</FullTextSearchOnInputByString>
			<ChoiceDataGetModeOnInputByString>Directly</ChoiceDataGetModeOnInputByString>
			<CreateOnInput>DontUse</CreateOnInput>
			<DefaultObjectForm/>
			<DefaultListForm>Task.ЗадачаБилета.Form.ФормаСписка</DefaultListForm>
			<DefaultChoiceForm/>
			<AuxiliaryObjectForm/>
			<AuxiliaryListForm/>
			<AuxiliaryChoiceForm/>
			<ChoiceHistoryOnInput>Auto</ChoiceHistoryOnInput>
			<IncludeHelpInContents>false</IncludeHelpInContents>
			<DataLockFields/>
			<DataLockControlMode>Managed</DataLockControlMode>
			<FullTextSearch>Use</FullTextSearch>
			<ObjectPresentation/>
			<ExtendedObjectPresentation/>
			<ListPresentation/>
			<ExtendedListPresentation/>
			<Explanation/>
			<DataHistory>DontUse</DataHistory>
			<UpdateDataHistoryImmediatelyAfterWrite>false</UpdateDataHistoryImmediatelyAfterWrite>
			<ExecuteAfterWriteDataHistoryVersionProcessing>false</ExecuteAfterWriteDataHistoryVersionProcessing>
		</Properties>
		<ChildObjects>
			<Form>ФормаСпискаПоИсполнителю</Form>
			<Form>ФормаСписка</Form>
			<AddressingAttribute uuid="b3cf2bc5-d70c-4abe-a898-684a8e53af5c">
				<Properties>
					<Name>Исполнитель</Name>
					<Synonym>
						<v8:item>
							<v8:lang>ru</v8:lang>
							<v8:content>Исполнитель</v8:content>
						</v8:item>
					</Synonym>
					<Comment/>
					<Type>
						<v8:Type>cfg:CatalogRef.ФизическиеЛица</v8:Type>
					</Type>
					<PasswordMode>false</PasswordMode>
					<Format/>
					<EditFormat/>
					<ToolTip/>
					<MarkNegatives>false</MarkNegatives>
					<Mask/>
					<MultiLine>false</MultiLine>
					<ExtendedEdit>false</ExtendedEdit>
					<MinValue xsi:nil="true"/>
					<MaxValue xsi:nil="true"/>
					<FillFromFillingValue>false</FillFromFillingValue>
					<FillValue xsi:nil="true"/>
					<FillChecking>DontCheck</FillChecking>
					<ChoiceFoldersAndItems>Items</ChoiceFoldersAndItems>
					<ChoiceParameterLinks/>
					<ChoiceParameters/>
					<QuickChoice>Auto</QuickChoice>
					<CreateOnInput>Auto</CreateOnInput>
					<ChoiceForm/>
					<LinkByType/>
					<ChoiceHistoryOnInput>Auto</ChoiceHistoryOnInput>
					<Indexing>DontIndex</Indexing>
					<AddressingDimension>InformationRegister.РегистрАдресации.Dimension.Исполнитель</AddressingDimension>
					<FullTextSearch>Use</FullTextSearch>
					<DataHistory>Use</DataHistory>
				</Properties>
			</AddressingAttribute>
			<AddressingAttribute uuid="8689ce91-d189-406a-aa48-417780c6c3d9">
				<Properties>
					<Name>Должность</Name>
					<Synonym>
						<v8:item>
							<v8:lang>ru</v8:lang>
							<v8:content>Должность</v8:content>
						</v8:item>
					</Synonym>
					<Comment/>
					<Type>
						<v8:Type>cfg:CatalogRef.Должности</v8:Type>
					</Type>
					<PasswordMode>false</PasswordMode>
					<Format/>
					<EditFormat/>
					<ToolTip/>
					<MarkNegatives>false</MarkNegatives>
					<Mask/>
					<MultiLine>false</MultiLine>
					<ExtendedEdit>false</ExtendedEdit>
					<MinValue xsi:nil="true"/>
					<MaxValue xsi:nil="true"/>
					<FillFromFillingValue>false</FillFromFillingValue>
					<FillValue xsi:nil="true"/>
					<FillChecking>DontCheck</FillChecking>
					<ChoiceFoldersAndItems>Items</ChoiceFoldersAndItems>
					<ChoiceParameterLinks/>
					<ChoiceParameters/>
					<QuickChoice>Auto</QuickChoice>
					<CreateOnInput>Auto</CreateOnInput>
					<ChoiceForm/>
					<LinkByType/>
					<ChoiceHistoryOnInput>Auto</ChoiceHistoryOnInput>
					<Indexing>DontIndex</Indexing>
					<AddressingDimension>InformationRegister.РегистрАдресации.Dimension.Должность</AddressingDimension>
					<FullTextSearch>Use</FullTextSearch>
					<DataHistory>Use</DataHistory>
				</Properties>
			</AddressingAttribute>
			<AddressingAttribute uuid="5ff2c1bc-9380-4624-984e-557d5204352a">
				<Properties>
					<Name>Подразделение</Name>
					<Synonym>
						<v8:item>
							<v8:lang>ru</v8:lang>
							<v8:content>Подразделение</v8:content>
						</v8:item>
					</Synonym>
					<Comment/>
					<Type>
						<v8:Type>cfg:CatalogRef.Подразделения</v8:Type>
					</Type>
					<PasswordMode>false</PasswordMode>
					<Format/>
					<EditFormat/>
					<ToolTip/>
					<MarkNegatives>false</MarkNegatives>
					<Mask/>
					<MultiLine>false</MultiLine>
					<ExtendedEdit>false</ExtendedEdit>
					<MinValue xsi:nil="true"/>
					<MaxValue xsi:nil="true"/>
					<FillFromFillingValue>false</FillFromFillingValue>
					<FillValue xsi:nil="true"/>
					<FillChecking>DontCheck</FillChecking>
					<ChoiceFoldersAndItems>Items</ChoiceFoldersAndItems>
					<ChoiceParameterLinks/>
					<ChoiceParameters/>
					<QuickChoice>Auto</QuickChoice>
					<CreateOnInput>Auto</CreateOnInput>
					<ChoiceForm/>
					<LinkByType/>
					<ChoiceHistoryOnInput>Auto</ChoiceHistoryOnInput>
					<Indexing>DontIndex</Indexing>
					<AddressingDimension>InformationRegister.РегистрАдресации.Dimension.Подразделение</AddressingDimension>
					<FullTextSearch>Use</FullTextSearch>
					<DataHistory>Use</DataHistory>
				</Properties>
			</AddressingAttribute>
		</ChildObjects>
	</Task>
</MetaDataObject>