<?xml version="1.0" encoding="UTF-8"?>
<MetaDataObject xmlns="http://v8.1c.ru/8.3/MDClasses" xmlns:app="http://v8.1c.ru/8.2/managed-application/core" xmlns:cfg="http://v8.1c.ru/8.1/data/enterprise/current-config" xmlns:cmi="http://v8.1c.ru/8.2/managed-application/cmi" xmlns:ent="http://v8.1c.ru/8.1/data/enterprise" xmlns:lf="http://v8.1c.ru/8.2/managed-application/logform" xmlns:style="http://v8.1c.ru/8.1/data/ui/style" xmlns:sys="http://v8.1c.ru/8.1/data/ui/fonts/system" xmlns:v8="http://v8.1c.ru/8.1/data/core" xmlns:v8ui="http://v8.1c.ru/8.1/data/ui" xmlns:web="http://v8.1c.ru/8.1/data/ui/colors/web" xmlns:win="http://v8.1c.ru/8.1/data/ui/colors/windows" xmlns:xen="http://v8.1c.ru/8.3/xcf/enums" xmlns:xpr="http://v8.1c.ru/8.3/xcf/predef" xmlns:xr="http://v8.1c.ru/8.3/xcf/readable" xmlns:xs="http://www.w3.org/2001/XMLSchema" xmlns:xsi="http://www.w3.org/2001/XMLSchema-instance" version="2.11">
	<AccountingRegister uuid="f45fcaf5-459e-4e8d-bd50-471499bc88a9">
		<InternalInfo>
			<xr:GeneratedType name="AccountingRegisterRecord.Управленческий" category="Record">
				<xr:TypeId>0b18b319-417b-4909-a399-c6bb025e8c71</xr:TypeId>
				<xr:ValueId>8b5c3b88-943b-46b2-bd25-08bb72b1b70f</xr:ValueId>
			</xr:GeneratedType>
			<xr:GeneratedType name="AccountingRegisterExtDimensions.Управленческий" category="ExtDimensions">
				<xr:TypeId>5efea953-b7aa-4fe9-9b17-5bb05597e015</xr:TypeId>
				<xr:ValueId>f3aceb13-2d49-489a-aded-477c3e818d73</xr:ValueId>
			</xr:GeneratedType>
			<xr:GeneratedType name="AccountingRegisterRecordSet.Управленческий" category="RecordSet">
				<xr:TypeId>55f80767-a346-4d63-9f2f-b1c2bdb93bee</xr:TypeId>
				<xr:ValueId>ff202ffd-b13b-4fce-9eb7-00425a5519ed</xr:ValueId>
			</xr:GeneratedType>
			<xr:GeneratedType name="AccountingRegisterRecordKey.Управленческий" category="RecordKey">
				<xr:TypeId>37400d89-c656-481f-b4ea-4e40de280400</xr:TypeId>
				<xr:ValueId>b64a8e52-0b67-4a06-99ba-87a367af249f</xr:ValueId>
			</xr:GeneratedType>
			<xr:GeneratedType name="AccountingRegisterSelection.Управленческий" category="Selection">
				<xr:TypeId>a9fbba17-e422-4c7c-86fa-6380d7278277</xr:TypeId>
				<xr:ValueId>648e9fea-2f38-4b18-91f7-7c4987f68c0c</xr:ValueId>
			</xr:GeneratedType>
			<xr:GeneratedType name="AccountingRegisterList.Управленческий" category="List">
				<xr:TypeId>020331f4-53a9-4a37-a0af-203528796354</xr:TypeId>
				<xr:ValueId>771a3dbd-12e1-4d03-b325-15b1be57917d</xr:ValueId>
			</xr:GeneratedType>
			<xr:GeneratedType name="AccountingRegisterManager.Управленческий" category="Manager">
				<xr:TypeId>62d6ab72-347f-467b-8d12-982cef9a3b6b</xr:TypeId>
				<xr:ValueId>b06e73f3-b972-4afc-886e-ad2d612de581</xr:ValueId>
			</xr:GeneratedType>
		</InternalInfo>
		<Properties>
			<Name>Управленческий</Name>
			<Synonym>
				<v8:item>
					<v8:lang>ru</v8:lang>
					<v8:content>Управленческий</v8:content>
				</v8:item>
			</Synonym>
			<Comment/>
			<UseStandardCommands>true</UseStandardCommands>
			<IncludeHelpInContents>false</IncludeHelpInContents>
			<ChartOfAccounts>ChartOfAccounts.Управленческий</ChartOfAccounts>
			<Correspondence>true</Correspondence>
			<PeriodAdjustmentLength>0</PeriodAdjustmentLength>
			<DefaultListForm/>
			<AuxiliaryListForm/>
			<DataLockControlMode>Managed</DataLockControlMode>
			<EnableTotalsSplitting>true</EnableTotalsSplitting>
			<FullTextSearch>DontUse</FullTextSearch>
			<ListPresentation/>
			<ExtendedListPresentation/>
			<Explanation/>
		</Properties>
		<ChildObjects>
			<Resource uuid="bca6756c-79e7-4b52-8fce-07e007bbd9c1">
				<Properties>
					<Name>Сумма</Name>
					<Synonym>
						<v8:item>
							<v8:lang>ru</v8:lang>
							<v8:content>Сумма</v8:content>
						</v8:item>
					</Synonym>
					<Comment/>
					<Type>
						<v8:Type>xs:decimal</v8:Type>
						<v8:NumberQualifiers>
							<v8:Digits>12</v8:Digits>
							<v8:FractionDigits>2</v8:FractionDigits>
							<v8:AllowedSign>Any</v8:AllowedSign>
						</v8:NumberQualifiers>
					</Type>
					<PasswordMode>false</PasswordMode>
					<Format/>
					<EditFormat/>
					<ToolTip/>
					<MarkNegatives>false</MarkNegatives>
					<Mask/>
					<MultiLine>false</MultiLine>
					<ExtendedEdit>false</ExtendedEdit>
					<MinValue xsi:nil="true"/>
					<MaxValue xsi:nil="true"/>
					<FillChecking>DontCheck</FillChecking>
					<ChoiceFoldersAndItems>Items</ChoiceFoldersAndItems>
					<ChoiceParameterLinks/>
					<ChoiceParameters/>
					<QuickChoice>Auto</QuickChoice>
					<CreateOnInput>Auto</CreateOnInput>
					<ChoiceForm/>
					<LinkByType/>
					<ChoiceHistoryOnInput>Auto</ChoiceHistoryOnInput>
					<Balance>true</Balance>
					<AccountingFlag/>
					<ExtDimensionAccountingFlag/>
					<FullTextSearch>Use</FullTextSearch>
				</Properties>
			</Resource>
			<Resource uuid="0cd77beb-9c64-46e5-ae7b-b75a74eaa8a6">
				<Properties>
					<Name>Количество</Name>
					<Synonym>
						<v8:item>
							<v8:lang>ru</v8:lang>
							<v8:content>Количество</v8:content>
						</v8:item>
					</Synonym>
					<Comment/>
					<Type>
						<v8:Type>xs:decimal</v8:Type>
						<v8:NumberQualifiers>
							<v8:Digits>10</v8:Digits>
							<v8:FractionDigits>0</v8:FractionDigits>
							<v8:AllowedSign>Any</v8:AllowedSign>
						</v8:NumberQualifiers>
					</Type>
					<PasswordMode>false</PasswordMode>
					<Format/>
					<EditFormat/>
					<ToolTip/>
					<MarkNegatives>false</MarkNegatives>
					<Mask/>
					<MultiLine>false</MultiLine>
					<ExtendedEdit>false</ExtendedEdit>
					<MinValue xsi:nil="true"/>
					<MaxValue xsi:nil="true"/>
					<FillChecking>DontCheck</FillChecking>
					<ChoiceFoldersAndItems>Items</ChoiceFoldersAndItems>
					<ChoiceParameterLinks/>
					<ChoiceParameters/>
					<QuickChoice>Auto</QuickChoice>
					<CreateOnInput>Auto</CreateOnInput>
					<ChoiceForm/>
					<LinkByType/>
					<ChoiceHistoryOnInput>Auto</ChoiceHistoryOnInput>
					<Balance>false</Balance>
					<AccountingFlag>ChartOfAccounts.Управленческий.AccountingFlag.Количественный</AccountingFlag>
					<ExtDimensionAccountingFlag/>
					<FullTextSearch>Use</FullTextSearch>
				</Properties>
			</Resource>
		</ChildObjects>
	</AccountingRegister>
</MetaDataObject>